flake8_import_order_tridge.py
flake8_import_order_tridge-1.0.5.dist-info/LICENSE
flake8_import_order_tridge-1.0.5.dist-info/METADATA
flake8_import_order_tridge-1.0.5.dist-info/WHEEL
flake8_import_order_tridge-1.0.5.dist-info/entry_points.txt
flake8_import_order_tridge-1.0.5.dist-info/top_level.txt
flake8_import_order_tridge-1.0.5.dist-info/RECORD
